AUTHORS
MANIFEST.in
README.rst
setup.py
django_flickr.egg-info/PKG-INFO
django_flickr.egg-info/SOURCES.txt
django_flickr.egg-info/dependency_links.txt
django_flickr.egg-info/not-zip-safe
django_flickr.egg-info/requires.txt
django_flickr.egg-info/top_level.txt
flickr/__init__.py
flickr/admin.py
flickr/api.py
flickr/flickr_spec.py
flickr/models.py
flickr/shortcuts.py
flickr/tests.py
flickr/tests_data.py
flickr/urls.py
flickr/utils.py
flickr/views.py
flickr/management/__init__.py
flickr/management/commands/__init__.py
flickr/management/commands/flickr_download.py
flickr/management/commands/flickr_sync.py
flickr/migrations/0001_initial.py
flickr/migrations/0002_auto__add_collection.py
flickr/migrations/0003_auto__add_photodownload.py
flickr/migrations/0004_add_photo_originalformat.py
flickr/migrations/0005_auto__add_photosizedata__add_unique_photosizedata_photo_size__del_fiel.py
flickr/migrations/0006_auto__add_field_flickruser_ispro.py
flickr/migrations/0007_auto__del_field_photodownload_ori__add_field_photodownload_size.py
flickr/migrations/0008_auto__add_field_flickruser_tzoffset.py
flickr/migrations/0008_consistent_last_sync.py
flickr/migrations/0009_expand_size_maxlength.py
flickr/migrations/__init__.py
flickr/templatetags/__init__.py
flickr/templatetags/flickr_tags.py