Metadata-Version: 1.1
Name: django-flickr
Version: 0.3.5
Summary: Mirror your Flickr into Django.
Home-page: https://bitbucket.org/zalew/django-flickr
Author: Jakub Zalewski
Author-email: zalew7@gmail.com
License: BSD license
Keywords: django flickr photo photography photoblog
Platform: UNKNOWN
Classifier: Development Status :: 3 - Alpha
Classifier: Environment :: Web Environment
Classifier: Intended Audience :: Developers
Classifier: License :: OSI Approved :: BSD License
Classifier: Operating System :: OS Independent
Classifier: Programming Language :: Python
Classifier: Programming Language :: Python :: 2
Classifier: Framework :: Django
